MANIFEST.in
README.rst
setup.py
django_doberman.egg-info/PKG-INFO
django_doberman.egg-info/SOURCES.txt
django_doberman.egg-info/dependency_links.txt
django_doberman.egg-info/pbr.json
django_doberman.egg-info/requires.txt
django_doberman.egg-info/top_level.txt
doberman/__init__.py
doberman/admin.py
doberman/auth.py
doberman/decorators.py
doberman/exceptions.py
doberman/models.py
doberman/settings.py
doberman/views.py
doberman/contrib/__init__.py
doberman/contrib/ipware.py
doberman/contrib/captcha/__init__.py
doberman/contrib/captcha/_compat.py
doberman/contrib/captcha/client.py
doberman/contrib/captcha/fields.py
doberman/contrib/captcha/widgets.py
doberman/migrations/0001_initial.py
doberman/migrations/0002_auto_20150721_1431.py
doberman/migrations/0003_auto_20150722_1652.py
doberman/migrations/__init__.py
doberman/templates/doberman/ip_lockout.html
doberman/tests/__init__.py
doberman/tests/test_access.py
doberman/tests/test_settings.py
doberman/tests/test_urls.py
doberman/tests/templates/base.html
doberman/tests/templates/login.html