Metadata-Version: 1.1
Name: django-doberman
Version: 0.5.9
Summary: Django app that locks out users after too many failed login attempts.
Home-page: https://github.com/nicchub/django-doberman
Author: Nicolas Mendoza
Author-email: niccolasmendoza@gmail.com
License: MIT License
Keywords: django locks users account login attempts banned ip doberman authentication
Platform: UNKNOWN
Classifier: Development Status :: 1 - Planning
Classifier: Intended Audience :: Developers
Classifier: License :: OSI Approved :: MIT License
Classifier: Natural Language :: English
Classifier: Programming Language :: Python
Classifier: Programming Language :: Python :: 2.6
Classifier: Programming Language :: Python :: 2.7
Classifier: Programming Language :: Python :: 3.2
Classifier: Framework :: Django
Classifier: Framework :: Django :: 1.7
Classifier: Framework :: Django :: 1.8
Classifier: Topic :: Software Development
Classifier: Topic :: Software Development :: Libraries
